terminalcolorpy/__init__.py
terminalcolorpy/tcp.py
terminalcolorpy-1.0.0.dist-info/LICENSE
terminalcolorpy-1.0.0.dist-info/METADATA
terminalcolorpy-1.0.0.dist-info/WHEEL
terminalcolorpy-1.0.0.dist-info/top_level.txt
terminalcolorpy-1.0.0.dist-info/RECORD
