Metadata-Version: 2.1
Name: terminalcolorpy
Version: 1.0.0
Summary: Lightweight package to print colorized messages using ASCI escape sequences to the terminal.
Home-page: https://github.com/novusys/terminalcolorpy/
Author: novusys
Author-email: novusys <amarftw1@gmail.com>
License: MIT License        
Project-URL: Homepage, https://github.com/novusys/terminalcolorpy/
Project-URL: Bug Tracker, https://github.com/novusys/terminalcolorpy/issues
Classifier: Intended Audience :: Developers
Classifier: Topic :: Software Development :: Build Tools
Classifier: License :: OSI Approved :: MIT License
Classifier: Programming Language :: Python :: 3.10
Classifier: Operating System :: OS Independent
Requires-Python: >=3.10
License-File: LICENSE
